lndb/__init__.py
lndb/__main__.py
lndb/_check_instance_setup.py
lndb/_check_versions.py
lndb/_close.py
lndb/_delete.py
lndb/_info.py
lndb/_init_instance.py
lndb/_load_instance.py
lndb/_notebook.py
lndb/_register_instance.py
lndb/_schema.py
lndb/_set.py
lndb/_settings.py
lndb/_settings_load.py
lndb/_settings_store.py
lndb/_setup_user.py
lndb/_assets/__init__.py
lndb/_migrate/__init__.py
lndb/_migrate/alembic.ini
lndb/_migrate/core.py
lndb/_migrate/deploy.py
lndb/_migrate/env.py
lndb/_migrate/script.py.mako
lndb/_migrate/utils.py
lndb/dev/__init__.py
lndb/dev/_clone.py
lndb/dev/_db.py
lndb/dev/_deprecated.py
lndb/dev/_docs.py
lndb/dev/_exclusion.py
lndb/dev/_settings_instance.py
lndb/dev/_settings_load.py
lndb/dev/_settings_save.py
lndb/dev/_settings_store.py
lndb/dev/_settings_user.py
lndb/dev/_setup_knowledge.py
lndb/dev/_setup_schema.py
lndb/dev/_storage.py
lndb/dev/upath.py
lndb/test/__init__.py
lndb/test/_env.py
lndb/test/_migrations_e2e.py
lndb/test/_migrations_unit.py
lndb/test/_nox.py
lndb/test/nox.py
lndb-0.45.0.dist-info/entry_points.txt
lndb-0.45.0.dist-info/LICENSE
lndb-0.45.0.dist-info/WHEEL
lndb-0.45.0.dist-info/METADATA
lndb-0.45.0.dist-info/RECORD
