Metadata-Version: 2.1
Name: lndb
Version: 0.45.0
Summary: LaminDB setup.
Author-email: Lamin Labs <laminlabs@gmail.com>
Requires-Dist: lnhub_rest==0.9.8
Requires-Dist: laminci>=0.3.0
Requires-Dist: lnschema_core>=0.34a2
Requires-Dist: lamin_logger>=0.2.3
Requires-Dist: pytest_alembic==0.9.1
Requires-Dist: sqlmodel>=0.0.8
Requires-Dist: psycopg2-binary
Requires-Dist: appdirs
Requires-Dist: python-dotenv
Requires-Dist: erdiagram
Requires-Dist: alembic
Requires-Dist: natsort
Requires-Dist: pandas
Requires-Dist: python-dateutil
Requires-Dist: universal_pathlib
Requires-Dist: pre-commit ; extra == "dev"
Requires-Dist: nox ; extra == "dev"
Requires-Dist: pytest>=6.0 ; extra == "test"
Requires-Dist: pytest-cov ; extra == "test"
Requires-Dist: nbproject-test>=0.4.3 ; extra == "test"
Requires-Dist: nbproject ; extra == "test"
Project-URL: Home, https://github.com/laminlabs/lndb
Provides-Extra: dev
Provides-Extra: test
